LICENSE.txt
MANIFEST.in
README.rst
setup.py
django_fs_smsaero.egg-info/PKG-INFO
django_fs_smsaero.egg-info/SOURCES.txt
django_fs_smsaero.egg-info/dependency_links.txt
django_fs_smsaero.egg-info/requires.txt
django_fs_smsaero.egg-info/top_level.txt
smsaero/__init__.py
smsaero/admin.py
smsaero/api.py
smsaero/exceptions.py
smsaero/models.py
smsaero/settings.py
smsaero/locale/ru/LC_MESSAGES/django.mo
smsaero/locale/ru/LC_MESSAGES/django.po
smsaero/management/__init__.py
smsaero/management/commands/__init__.py
smsaero/management/commands/smsaero_status.py
smsaero/migrations/0001_initial.py
smsaero/migrations/0002_auto__add_message.py
smsaero/migrations/__init__.py